envs/__init__.py
gym2_fearbun/__init__.py
gym2_fearbun/envs/__init__.py
gym2_fearbun/envs/random_walk/__init__.py
gym2_fearbun/envs/random_walk/random_walk.py
gym_fearbun2/__init__.py
gym_fearbun2/envs/__init__.py
gym_fearbun2/envs/random_walk/__init__.py
gym_fearbun2/envs/random_walk/random_walk.py
gym2_fearbun-0.0.4.dist-info/METADATA
gym2_fearbun-0.0.4.dist-info/WHEEL
gym2_fearbun-0.0.4.dist-info/top_level.txt
gym2_fearbun-0.0.4.dist-info/RECORD
