Metadata-Version: 2.1
Name: gym2-fearbun
Version: 0.0.4
Summary: UNKNOWN
Home-page: UNKNOWN
License: UNKNOWN
Platform: UNKNOWN
Requires-Python: >=3.7.5
Requires-Dist: gym
